odoo/addons/account_bank_statement_import_oca_camt54/README.rst
odoo/addons/account_bank_statement_import_oca_camt54/__init__.py
odoo/addons/account_bank_statement_import_oca_camt54/__manifest__.py
odoo/addons/account_bank_statement_import_oca_camt54/i18n/account_bank_statement_import_oca_camt54.pot
odoo/addons/account_bank_statement_import_oca_camt54/models/__init__.py
odoo/addons/account_bank_statement_import_oca_camt54/models/account_bank_statement_import.py
odoo/addons/account_bank_statement_import_oca_camt54/models/parser.py
odoo/addons/account_bank_statement_import_oca_camt54/readme/CONTRIBUTORS.rst
odoo/addons/account_bank_statement_import_oca_camt54/readme/DESCRIPTION.rst
odoo/addons/account_bank_statement_import_oca_camt54/static/description/icon.png
odoo/addons/account_bank_statement_import_oca_camt54/static/description/index.html
odoo/addons/account_bank_statement_import_oca_camt54/tests/__init__.py
odoo/addons/account_bank_statement_import_oca_camt54/tests/test_get_partner_ref.py
odoo13_addon_account_bank_statement_import_oca_camt54-13.0.1.0.1.dev6.dist-info/METADATA
odoo13_addon_account_bank_statement_import_oca_camt54-13.0.1.0.1.dev6.dist-info/WHEEL
odoo13_addon_account_bank_statement_import_oca_camt54-13.0.1.0.1.dev6.dist-info/top_level.txt
odoo13_addon_account_bank_statement_import_oca_camt54-13.0.1.0.1.dev6.dist-info/RECORD
